element_interface/__init__.py
element_interface/caiman_loader.py
element_interface/dandi.py
element_interface/extract_loader.py
element_interface/extract_trigger.py
element_interface/prairie_view_loader.py
element_interface/run_caiman.py
element_interface/scanimage_utils.py
element_interface/suite2p_loader.py
element_interface/suite2p_trigger.py
element_interface/utils.py
element_interface/version.py
element_interface-0.6.1.dist-info/LICENSE
element_interface-0.6.1.dist-info/METADATA
element_interface-0.6.1.dist-info/WHEEL
element_interface-0.6.1.dist-info/top_level.txt
element_interface-0.6.1.dist-info/RECORD
