Metadata-Version: 2.1
Name: element-interface
Version: 0.6.1
Summary: Loaders of neurophysiological data into the DataJoint Elements
Home-page: https://github.com/datajoint/element-interface
Author: DataJoint
Author-email: info@datajoint.com
License: MIT
Keywords: neuroscience calcium-imaging science datajoint
Platform: UNKNOWN
License-File: LICENSE
Requires-Dist: dandi
Requires-Dist: numpy
